Metadata-Version: 2.4
Name: vntyper
Version: 2.0.0b3
Summary: VNtyper: A tool for genotyping MUC1-VNTR
Author-email: Hassan Saei <hassan.saei@inserm.fr>, Bernt Popp <bernt.popp.md@gmail.com>
License: MIT
Project-URL: Homepage, https://github.com/hassansaei/vntyper
Project-URL: Repository, https://github.com/hassansaei/vntyper
Project-URL: Issues, https://github.com/hassansaei/vntyper/issues
Project-URL: Documentation, https://github.com/hassansaei/vntyper#readme
Keywords: bioinformatics,genomics,VNTR,MUC1,genotyping
Classifier: Development Status :: 4 - Beta
Classifier: Intended Audience :: Science/Research
Classifier: Topic :: Scientific/Engineering :: Bio-Informatics
Classifier: Programming Language :: Python :: 3
Classifier: Programming Language :: Python :: 3.9
Classifier: Programming Language :: Python :: 3.10
Classifier: Programming Language :: Python :: 3.11
Classifier: Programming Language :: Python :: 3.12
Classifier: License :: OSI Approved :: MIT License
Classifier: Operating System :: OS Independent
Requires-Python: >=3.9
License-File: LICENSE
Requires-Dist: pandas<2.3.0,>=2.2.0
Requires-Dist: numpy<2.0.0,>=1.26.0
Requires-Dist: regex>=2024.7.24
Requires-Dist: biopython>=1.84
Requires-Dist: setuptools>=72.2.0
Requires-Dist: pysam>=0.22.1
Requires-Dist: jinja2>=3.1.0
Requires-Dist: matplotlib>=3.9.0
Requires-Dist: seaborn>=0.13.0
Requires-Dist: igv-reports>=1.13.0
Requires-Dist: plotly>=5.24.0
Provides-Extra: dev
Requires-Dist: pytest>=7.0; extra == "dev"
Requires-Dist: pytest-cov>=4.0; extra == "dev"
Requires-Dist: pytest-timeout>=2.3.0; extra == "dev"
Requires-Dist: pytest-xdist>=3.0; extra == "dev"
Requires-Dist: testcontainers>=4.0.0; extra == "dev"
Requires-Dist: requests>=2.31.0; extra == "dev"
Requires-Dist: ruff>=0.8.0; extra == "dev"
Requires-Dist: mypy>=1.0.0; extra == "dev"
Requires-Dist: types-requests>=2.0.0; extra == "dev"
Dynamic: license-file
